pycronjob/__init__.py
pycronjob/pycronjob.py
pycronjob-1.2.2.dist-info/METADATA
pycronjob-1.2.2.dist-info/WHEEL
pycronjob-1.2.2.dist-info/top_level.txt
pycronjob-1.2.2.dist-info/RECORD
