Metadata-Version: 2.1
Name: pycronjob
Version: 1.2.2
Summary: An easy to start crontab
Home-page: http://git.yonyou.com/iuapaipaas/iw-algo-fx
Author: hexergogo
Author-email: hexu0614@gmail.com
License: UNKNOWN
Platform: UNKNOWN
Classifier: Development Status :: 3 - Alpha
Classifier: Programming Language :: Python :: 3.5
Classifier: Programming Language :: Python :: 3.6
Classifier: Programming Language :: Python :: 3.7
Classifier: Programming Language :: Python :: 3.8
Classifier: Programming Language :: Python :: 3.9
Classifier: Programming Language :: Python :: 3.10
Classifier: Operating System :: OS Independent
Requires-Python: >=3.5
Requires-Dist: apscheduler (==3.9.1)
